{
	"instance" : {
		"initializeValues" : "MaximilianoTabacman 8/14/2016 00:56",
		"adjustBehaviorAfter:accordingTo:" : "MaximilianoTabacman 8/14/2016 00:57",
		"initializeExperiences" : "MaximilianoTabacman 8/14/2016 00:56",
		"maximumValue" : "MaximilianoTabacman 8/14/2016 00:56",
		"shouldExplore" : "MaximilianoTabacman 8/14/2016 00:57",
		"updatedQualityAfter:" : "MaximilianoTabacman 8/14/2016 00:56",
		"adjustBehaviorAfter:" : "MaximilianoTabacman 8/14/2016 00:57",
		"actionWhenIn:" : "MaximilianoTabacman 8/14/2016 00:55",
		"process:" : "MaximilianoTabacman 8/14/2016 00:57",
		"adjustBehaviorAfterDoing:in:receiving:endingIn:" : "MaximilianoTabacman 8/14/2016 00:56",
		"replayExperiences" : "MaximilianoTabacman 8/14/2016 00:57",
		"estimating:" : "MaximilianoTabacman 8/14/2016 00:56",
		"initializeQualities" : "MaximilianoTabacman 8/14/2016 00:56",
		"initializePolicy" : "MaximilianoTabacman 8/14/2016 00:56",
		"maximumQualityFor:" : "MaximilianoTabacman 8/14/2016 00:56",
		"initializeEstimating:allowing:discountingAt:learningAt:exploringWithProbability:" : "MaximilianoTabacman 8/14/2016 00:55",
		"exploringAction" : "MaximilianoTabacman 8/14/2016 00:56",
		"discardExperiences" : "MaximilianoTabacman 8/14/2016 00:56"
	},
	"class" : {
		"estimating:allowing:discountingAt:learningAt:exploringWithProbability:" : "MaximilianoTabacman 8/14/2016 00:52"
	}
}