{
	"instance" : {
		"estimatedValueFor:" : "MaximilianoTabacman 8/14/2016 01:19",
		"actionWhenIn:" : "MaximilianoTabacman 8/14/2016 01:19",
		"adjustPolicyFor:" : "MaximilianoTabacman 8/14/2016 01:20",
		"adjustBehaviorAfterDoing:in:receiving:endingIn:" : "MaximilianoTabacman 8/14/2016 01:20",
		"adjustPolicy" : "MaximilianoTabacman 8/14/2016 01:20",
		"adjustExperienceValues" : "MaximilianoTabacman 8/14/2016 01:20",
		"estimating:" : "MaximilianoTabacman 8/14/2016 01:20",
		"initializeExperiencies" : "MaximilianoTabacman 8/14/2016 01:19",
		"discountRate" : "MaximilianoTabacman 8/14/2016 01:19",
		"maximumReinforcement" : "MaximilianoTabacman 8/14/2016 01:19",
		"initializePolicy" : "MaximilianoTabacman 8/14/2016 01:19",
		"initializeEstimating:allowing:discountingAt:" : "MaximilianoTabacman 8/14/2016 01:19",
		"initializeValues" : "MaximilianoTabacman 8/14/2016 01:19"
	},
	"class" : {
		"estimating:allowing:discountingAt:" : "MaximilianoTabacman 8/14/2016 01:19"
	}
}